moretunes/youtube/__init__.py
moretunes/youtube/constants.py
moretunes/youtube/continuations.py
moretunes/youtube/exceptions.py
moretunes/youtube/helpers.py
moretunes/youtube/navigation.py
moretunes/youtube/setup.py
moretunes/youtube/speed_nav.py
moretunes/youtube/ytmusic.py
moretunes/youtube/auth/__init__.py
moretunes/youtube/auth/browser.py
moretunes/youtube/auth/types.py
moretunes/youtube/auth/oauth/__init__.py
moretunes/youtube/auth/oauth/credentials.py
moretunes/youtube/auth/oauth/exceptions.py
moretunes/youtube/auth/oauth/models.py
moretunes/youtube/auth/oauth/refreshing.py
moretunes/youtube/auth/oauth/token.py
moretunes/youtube/locales/README.rst
moretunes/youtube/locales/ar/LC_MESSAGES/base.mo
moretunes/youtube/locales/de/LC_MESSAGES/base.mo
moretunes/youtube/locales/en/LC_MESSAGES/base.mo
moretunes/youtube/locales/es/LC_MESSAGES/base.mo
moretunes/youtube/locales/fr/LC_MESSAGES/base.mo
moretunes/youtube/locales/hi/LC_MESSAGES/base.mo
moretunes/youtube/locales/it/LC_MESSAGES/base.mo
moretunes/youtube/locales/ja/LC_MESSAGES/base.mo
moretunes/youtube/locales/ko/LC_MESSAGES/base.mo
moretunes/youtube/locales/nl/LC_MESSAGES/base.mo
moretunes/youtube/locales/pt/LC_MESSAGES/base.mo
moretunes/youtube/locales/ru/LC_MESSAGES/base.mo
moretunes/youtube/locales/tr/LC_MESSAGES/base.mo
moretunes/youtube/locales/ur/LC_MESSAGES/base.mo
moretunes/youtube/locales/zh_CN/LC_MESSAGES/base.mo
moretunes/youtube/locales/zh_TW/LC_MESSAGES/base.mo
moretunes/youtube/mixins/__init__.py
moretunes/youtube/mixins/_protocol.py
moretunes/youtube/mixins/_utils.py
moretunes/youtube/mixins/browsing.py
moretunes/youtube/mixins/explore.py
moretunes/youtube/mixins/library.py
moretunes/youtube/mixins/playlists.py
moretunes/youtube/mixins/search.py
moretunes/youtube/mixins/uploads.py
moretunes/youtube/mixins/watch.py
moretunes/youtube/models/__init__.py
moretunes/youtube/models/base.py
moretunes/youtube/models/browsing.py
moretunes/youtube/parsers/__init__.py
moretunes/youtube/parsers/albums.py
moretunes_youtube-0.2.6rc12.dev1.dist-info/LICENSE
moretunes_youtube-0.2.6rc12.dev1.dist-info/METADATA
moretunes_youtube-0.2.6rc12.dev1.dist-info/WHEEL
moretunes_youtube-0.2.6rc12.dev1.dist-info/entry_points.txt
moretunes_youtube-0.2.6rc12.dev1.dist-info/top_level.txt
moretunes_youtube-0.2.6rc12.dev1.dist-info/RECORD
