Metadata-Version: 2.1
Name: moretunes-youtube
Version: 0.2.6rc12.dev1
Summary: Unofficial API for YouTube Music submodule for moretunes
Author-email: jcbirdwell <j.c.birdwell@gmail.com>
License: MIT License
Classifier: Programming Language :: Python :: 3
Classifier: License :: OSI Approved :: MIT License
Classifier: Development Status :: 3 - Alpha
Requires-Python: >=3.8
License-File: LICENSE
Requires-Dist: requests >=2.22
Requires-Dist: pydantic >=2.6.1
